macos_notification_mcp/__init__.py
macos_notification_mcp/server.py
macos_notification_mcp-0.1.1.dist-info/licenses/LICENSE
macos_notification_mcp-0.1.1.dist-info/METADATA
macos_notification_mcp-0.1.1.dist-info/WHEEL
macos_notification_mcp-0.1.1.dist-info/entry_points.txt
macos_notification_mcp-0.1.1.dist-info/top_level.txt
macos_notification_mcp-0.1.1.dist-info/RECORD
