Metadata-Version: 2.4
Name: macos-notification-mcp
Version: 0.1.1
Summary: macOS Notification MCP Server with sound, banner, and speech alerts
Author: Phatchara Maichandi
License: MIT
Classifier: Programming Language :: Python :: 3
Classifier: License :: OSI Approved :: MIT License
Classifier: Operating System :: MacOS
Requires-Python: >=3.9
License-File: LICENSE
Requires-Dist: fastmcp>=1.0.0
Dynamic: license-file
